mjpeg_streamer/__init__.py
mjpeg_streamer/mjpeg_streamer.py
mjpeg_streamer-2023.12.25.post0.dist-info/METADATA
mjpeg_streamer-2023.12.25.post0.dist-info/WHEEL
mjpeg_streamer-2023.12.25.post0.dist-info/licenses/LICENSE
mjpeg_streamer-2023.12.25.post0.dist-info/RECORD
