Metadata-Version: 2.1
Name: mjpeg-streamer
Version: 2023.12.25.post0
Summary: Simple, flexible and efficient MJPEG video streamer for Python
Project-URL: Homepage, https://github.com/egeakman/mjpeg-streamer
Project-URL: Issues, https://github.com/egeakman/mjpeg-streamer/issues
Project-URL: Releases, https://github.com/egeakman/mjpeg-streamer/releases
Author-email: Ege Akman <me@egeakman.dev>
License: AGPLv3
License-File: LICENSE
Keywords: MJPEG,OpenCV,aiohttp,asyncio,computer-vision,multi-camera,server,streamer,streaming,video,webcam
Classifier: Development Status :: 5 - Production/Stable
Classifier: Environment :: Web Environment
Classifier: Framework :: AsyncIO
Classifier: Framework :: aiohttp
Classifier: Intended Audience :: Developers
Classifier: Intended Audience :: System Administrators
Classifier: License :: OSI Approved :: GNU Affero General Public License v3 or later (AGPLv3+)
Classifier: Operating System :: MacOS :: MacOS X
Classifier: Operating System :: Microsoft :: Windows
Classifier: Operating System :: POSIX :: Linux
Classifier: Programming Language :: Python :: 3 :: Only
Classifier: Programming Language :: Python :: 3.6
Classifier: Programming Language :: Python :: 3.7
Classifier: Programming Language :: Python :: 3.8
Classifier: Programming Language :: Python :: 3.9
Classifier: Programming Language :: Python :: 3.10
Classifier: Programming Language :: Python :: 3.11
Classifier: Programming Language :: Python :: 3.12
Classifier: Topic :: Internet :: WWW/HTTP :: HTTP Servers
Classifier: Topic :: Multimedia :: Video
Classifier: Topic :: Security
Requires-Python: >=3.6
Requires-Dist: aiohttp; python_version >= '3.9'
Requires-Dist: aiohttp==3.8.6; python_version >= '3.6' and python_version <= '3.7'
Requires-Dist: aiohttp==3.9.1; python_version == '3.8'
Requires-Dist: netifaces
Requires-Dist: numpy; python_version >= '3.9'
Requires-Dist: numpy==1.19.5; python_version == '3.6'
Requires-Dist: numpy==1.21.6; python_version == '3.7'
Requires-Dist: numpy==1.24.4; python_version == '3.8'
Requires-Dist: opencv-python; python_version >= '3.9'
Requires-Dist: opencv-python==4.6.0.66; python_version == '3.6'
Requires-Dist: opencv-python==4.8.1.78; python_version >= '3.7' and python_version <= '3.8'
